README.md
pyproject.toml
setup.py
m_run_script.egg-info/PKG-INFO
m_run_script.egg-info/SOURCES.txt
m_run_script.egg-info/dependency_links.txt
m_run_script.egg-info/requires.txt
m_run_script.egg-info/top_level.txt
mobio/libs/run_script/__init__.py